starmerxauth_erp/__init__.py
starmerxauth_erp/middleware.py
starmerxauth_erp-0.2.6.dist-info/LICENSE
starmerxauth_erp-0.2.6.dist-info/METADATA
starmerxauth_erp-0.2.6.dist-info/WHEEL
starmerxauth_erp-0.2.6.dist-info/top_level.txt
starmerxauth_erp-0.2.6.dist-info/RECORD
