Metadata-Version: 2.1
Name: starmerxauth-erp
Version: 0.2.6
Summary: starmerx verify jwt in erp
Author: yang
Author-email: yangjuan@starmerx.com
License: UNKNOWN
Platform: UNKNOWN
Classifier: Programming Language :: Python
Classifier: License :: OSI Approved :: MIT License
Classifier: Operating System :: OS Independent
Requires-Python: >=2.7
License-File: LICENSE
Requires-Dist: PyJWT (>=1.7.1)
Requires-Dist: cryptography (>=2.7)
